mycalc/calculator.py
jkh011120_calc-0.0.1.dist-info/METADATA
jkh011120_calc-0.0.1.dist-info/WHEEL
jkh011120_calc-0.0.1.dist-info/top_level.txt
jkh011120_calc-0.0.1.dist-info/RECORD
