Metadata-Version: 2.1
Name: jkh011120-calc
Version: 0.0.1
Summary: nice calculator
Home-page: http://github.io/jkh011120/abc
Download-URL: http://github.com/jkh011120/abc/mm.zip
Author: jkh
License: UNKNOWN
Platform: UNKNOWN
Classifier: Programming Language :: Python :: 3
